clearskies_cortex/__init__.py
clearskies_cortex/dataclasses.py
clearskies_cortex/backends/__init__.py
clearskies_cortex/backends/cortex_backend.py
clearskies_cortex/backends/cortex_team_relationship_backend.py
clearskies_cortex/columns/__init__.py
clearskies_cortex/columns/string_list.py
clearskies_cortex/defaults/__init__.py
clearskies_cortex/defaults/default_cortex_auth.py
clearskies_cortex/defaults/default_cortex_url.py
clearskies_cortex/models/__init__.py
clearskies_cortex/models/cortex_catalog_entity.py
clearskies_cortex/models/cortex_catalog_entity_domain.py
clearskies_cortex/models/cortex_catalog_entity_group.py
clearskies_cortex/models/cortex_catalog_entity_scorecard.py
clearskies_cortex/models/cortex_catalog_entity_service.py
clearskies_cortex/models/cortex_catalog_entity_team.py
clearskies_cortex/models/cortex_catalog_entity_types.py
clearskies_cortex/models/cortex_entity_relationships.py
clearskies_cortex/models/cortex_model.py
clearskies_cortex/models/cortex_scorecard.py
clearskies_cortex/models/cortex_team.py
clearskies_cortex/models/cortex_team_category_tree.py
clearskies_cortex/models/cortex_team_department.py
clear_skies_cortex-2.0.2.dist-info/METADATA
clear_skies_cortex-2.0.2.dist-info/WHEEL
clear_skies_cortex-2.0.2.dist-info/licenses/LICENSE
clear_skies_cortex-2.0.2.dist-info/RECORD
